odoo10_addon_base_user_role_company-10.0.1.0.0.99.dev3-py3.8-nspkg.pth
odoo/addons/base_user_role_company/README.rst
odoo/addons/base_user_role_company/__init__.py
odoo/addons/base_user_role_company/__manifest__.py
odoo/addons/base_user_role_company/i18n/base_user_role_company.pot
odoo/addons/base_user_role_company/models/__init__.py
odoo/addons/base_user_role_company/models/ir_http.py
odoo/addons/base_user_role_company/models/role.py
odoo/addons/base_user_role_company/readme/CONFIGURE.rst
odoo/addons/base_user_role_company/readme/CONTRIBUTORS.rst
odoo/addons/base_user_role_company/readme/DESCRIPTION.rst
odoo/addons/base_user_role_company/readme/USAGE.rst
odoo/addons/base_user_role_company/static/description/icon.png
odoo/addons/base_user_role_company/static/description/index.html
odoo/addons/base_user_role_company/tests/__init__.py
odoo/addons/base_user_role_company/tests/test_role_per_company.py
odoo/addons/base_user_role_company/views/role.xml
odoo10_addon_base_user_role_company-10.0.1.0.0.99.dev3.dist-info/METADATA
odoo10_addon_base_user_role_company-10.0.1.0.0.99.dev3.dist-info/WHEEL
odoo10_addon_base_user_role_company-10.0.1.0.0.99.dev3.dist-info/namespace_packages.txt
odoo10_addon_base_user_role_company-10.0.1.0.0.99.dev3.dist-info/top_level.txt
odoo10_addon_base_user_role_company-10.0.1.0.0.99.dev3.dist-info/RECORD
